LICENSE
battery_advisor/__init__.py
battery_advisor/battery_advisor.py
battery_advisor/entry.py
battery_advisor/gui/alerts.py
battery_advisor/notifications.py
battery_advisor/settings_loader.py
battery_advisor/tray.py
battery_advisor/types.py
battery_advisor/utils.py
battery_advisor/version.py
defaultSettings.toml
icon.png
battery_advisor-1.2.1.dist-info/LICENSE
battery_advisor-1.2.1.dist-info/METADATA
battery_advisor-1.2.1.dist-info/WHEEL
battery_advisor-1.2.1.dist-info/entry_points.txt
battery_advisor-1.2.1.dist-info/RECORD
