Metadata-Version: 2.1
Name: battery-advisor
Version: 1.2.1
Summary: A simple tool to monitor and notify about battery status. Built with Python.
Home-page: https://github.com/fer-hnndz/battery-advisor
License: MIT
Keywords: battery,monitor,notify
Author: fer-hnndz
Author-email: 65425622+fer-hnndz@users.noreply.github.com
Requires-Python: >=3.11,<4.0
Classifier: Development Status :: 5 - Production/Stable
Classifier: License :: OSI Approved :: MIT License
Classifier: Operating System :: POSIX :: Linux
Classifier: Programming Language :: Python :: 3
Classifier: Programming Language :: Python :: 3.11
Classifier: Programming Language :: Python :: 3.12
Classifier: Topic :: Desktop Environment
Requires-Dist: psutil (>=6.0.0,<7.0.0)
Requires-Dist: pystray (>=0.19.5,<0.20.0)
Requires-Dist: toml (>=0.10.2,<0.11.0)
